tornado_rest_client/__init__.py
tornado_rest_client/api.py
tornado_rest_client/exceptions.py
tornado_rest_client/utils.py
tornado_rest_client/version.py
tornado_rest_client/clients/__init__.py
tornado_rest_client/clients/slack.py
tornado_rest_client/test/__init__.py
tornado_rest_client/test/integration_api.py
tornado_rest_client/test/test_api.py
tornado_rest_client/test/test_utils.py
tornado_rest_client/test/test_version.py
tornado_rest_client-2.0.2.dist-info/LICENSE
tornado_rest_client-2.0.2.dist-info/METADATA
tornado_rest_client-2.0.2.dist-info/WHEEL
tornado_rest_client-2.0.2.dist-info/top_level.txt
tornado_rest_client-2.0.2.dist-info/RECORD
