Metadata-Version: 2.1
Name: tornado_rest_client
Version: 2.0.2
Summary: Tornado REST client
Home-page: https://github.com/Nextdoor/tornado_rest_client
Download-URL: http://pypi.python.org/pypi/tornado_rest_client#downloads
Author: Nextdoor Engineering
License: Apache License, Version 2.0
Keywords: tornado,rest,tornado_rest_client
Classifier: Development Status :: 4 - Beta
Classifier: Intended Audience :: Developers
Classifier: License :: OSI Approved :: Apache Software License
Classifier: Natural Language :: English
Classifier: Operating System :: POSIX
Classifier: Programming Language :: Python :: 3
Classifier: Topic :: Software Development
Requires-Python: ~=3.7
License-File: LICENSE
Requires-Dist: tornado >=4.0.0
